{
	"credit": "Made with Blockbench",
	"textures": {
		"0": "qualityarmory:item/mando_sidearm",
		"particle": "qualityarmory:item/mando_sidearm"
	},
	"elements": [
		{
			"from": [7.5, 6.5, 7],
			"to": [8.5, 7, 9],
			"faces": {
				"north": {"uv": [0.5, 0.5, 1.5, 1.5], "texture": "#0"},
				"east": {"uv": [0.5, 0.5, 1.5, 1.5], "texture": "#0"},
				"south": {"uv": [0.5, 0.5, 1.5, 1.5], "texture": "#0"},
				"west": {"uv": [0.5, 0.5, 1.5, 1.5], "texture": "#0"},
				"up": {"uv": [0.5, 0.5, 1.5, 1.5], "texture": "#0"},
				"down": {"uv": [0.5, 0.5, 1.5, 1.5], "texture": "#0"}
			}
		},
		{
			"from": [7.5, 6.5, 9],
			"to": [8.5, 9, 10],
			"faces": {
				"north": {"uv": [0.5, 0.5, 1.5, 1.5], "texture": "#0"},
				"east": {"uv": [0.5, 0.5, 1.5, 1.5], "texture": "#0"},
				"south": {"uv": [0.5, 0.5, 1.5, 1.5], "texture": "#0"},
				"west": {"uv": [0.5, 0.5, 1.5, 1.5], "texture": "#0"},
				"up": {"uv": [0.5, 0.5, 1.5, 1.5], "texture": "#0"},
				"down": {"uv": [0.5, 0.5, 1.5, 1.5], "texture": "#0"}
			}
		},
		{
			"from": [7.5, 5.7929, 9],
			"to": [8.5, 6.5, 9.7071],
			"rotation": {"angle": -45, "axis": "x", "origin": [8, 6.5, 9]},
			"faces": {
				"north": {"uv": [0.5, 0.5, 1.5, 1.5], "texture": "#0"},
				"east": {"uv": [0.5, 0.5, 1.5, 1.5], "texture": "#0"},
				"south": {"uv": [0.5, 0.5, 1.5, 1.5], "texture": "#0"},
				"west": {"uv": [0.5, 0.5, 1.5, 1.5], "texture": "#0"},
				"up": {"uv": [0.5, 0.5, 1.5, 1.5], "texture": "#0"},
				"down": {"uv": [0.5, 0.5, 1.5, 1.5], "texture": "#0"}
			}
		},
		{
			"from": [7.625, 1.7929, 9],
			"to": [8.375, 6.7929, 11.5],
			"rotation": {"angle": -22.5, "axis": "x", "origin": [8, 6.5, 9]},
			"faces": {
				"north": {"uv": [0.5, 2.5, 1.5, 3.5], "texture": "#0"},
				"east": {"uv": [0.5, 2.5, 1.5, 3.5], "texture": "#0"},
				"south": {"uv": [0.5, 2.5, 1.5, 3.5], "texture": "#0"},
				"west": {"uv": [0.5, 2.5, 1.5, 3.5], "texture": "#0"},
				"up": {"uv": [0.5, 2.5, 1.5, 3.5], "texture": "#0"},
				"down": {"uv": [0.5, 2.5, 1.5, 3.5], "texture": "#0"}
			}
		},
		{
			"from": [7.625, 1.2929, 8.5],
			"to": [8.375, 1.7929, 11],
			"rotation": {"angle": -22.5, "axis": "x", "origin": [8, 6.5, 9]},
			"faces": {
				"north": {"uv": [0.5, 2.5, 1.5, 3.5], "texture": "#0"},
				"east": {"uv": [0.5, 2.5, 1.5, 3.5], "texture": "#0"},
				"south": {"uv": [0.5, 2.5, 1.5, 3.5], "texture": "#0"},
				"west": {"uv": [0.5, 2.5, 1.5, 3.5], "texture": "#0"},
				"up": {"uv": [0.5, 2.5, 1.5, 3.5], "texture": "#0"},
				"down": {"uv": [0.5, 2.5, 1.5, 3.5], "texture": "#0"}
			}
		},
		{
			"from": [7.62499, 1.37215, 12.29402],
			"to": [8.37499, 2.37215, 12.79402],
			"rotation": {"angle": 22.5, "axis": "x", "origin": [7.99999, 6.57925, 12.79402]},
			"faces": {
				"north": {"uv": [0.5, 2.5, 1.5, 3.5], "texture": "#0"},
				"east": {"uv": [0.5, 2.5, 1.5, 3.5], "texture": "#0"},
				"south": {"uv": [0.5, 2.5, 1.5, 3.5], "texture": "#0"},
				"west": {"uv": [0.5, 2.5, 1.5, 3.5], "texture": "#0"},
				"up": {"uv": [0.5, 2.5, 1.5, 3.5], "texture": "#0"},
				"down": {"uv": [0.5, 2.5, 1.5, 3.5], "texture": "#0"}
			}
		},
		{
			"from": [7.75, 0.7929, 8.25],
			"to": [8.25, 1.2929, 11],
			"rotation": {"angle": -22.5, "axis": "x", "origin": [8, 6.5, 9]},
			"faces": {
				"north": {"uv": [0.5, 0.5, 1.5, 1.5], "texture": "#0"},
				"east": {"uv": [0.5, 0.5, 1.5, 1.5], "texture": "#0"},
				"south": {"uv": [0.5, 0.5, 1.5, 1.5], "texture": "#0"},
				"west": {"uv": [0.5, 0.5, 1.5, 1.5], "texture": "#0"},
				"up": {"uv": [0.5, 0.5, 1.5, 1.5], "texture": "#0"},
				"down": {"uv": [0.5, 0.5, 1.5, 1.5], "texture": "#0"}
			}
		},
		{
			"from": [7.5, 1.0429, 10.25],
			"to": [8.5, 1.5429, 10.75],
			"rotation": {"angle": -22.5, "axis": "x", "origin": [8, 6.5, 9]},
			"faces": {
				"north": {"uv": [2.5, 2.5, 5.5, 5.5], "texture": "#0"},
				"east": {"uv": [2.5, 2.5, 5.5, 5.5], "texture": "#0"},
				"south": {"uv": [2.5, 2.5, 5.5, 5.5], "texture": "#0"},
				"west": {"uv": [2.5, 2.5, 5.5, 5.5], "texture": "#0"},
				"up": {"uv": [2.5, 2.5, 5.5, 5.5], "texture": "#0"},
				"down": {"uv": [2.5, 2.5, 5.5, 5.5], "texture": "#0"}
			}
		},
		{
			"from": [7.625, 2.82363, 13.98536],
			"to": [8.37498, 3.53073, 14.98534],
			"rotation": {"angle": 22.5, "axis": "x", "origin": [7.99998, 8.03073, 12.98536]},
			"faces": {
				"north": {"uv": [0.5, 2.5, 1.5, 3.5], "texture": "#0"},
				"east": {"uv": [0.5, 2.5, 1.5, 3.5], "texture": "#0"},
				"south": {"uv": [0.5, 2.5, 1.5, 3.5], "texture": "#0"},
				"west": {"uv": [0.5, 2.5, 1.5, 3.5], "texture": "#0"},
				"up": {"uv": [0.5, 2.5, 1.5, 3.5], "texture": "#0"},
				"down": {"uv": [0.5, 2.5, 1.5, 3.5], "texture": "#0"}
			}
		},
		{
			"from": [7.5, 8, 10],
			"to": [8.5, 9, 13],
			"faces": {
				"north": {"uv": [0.5, 0.5, 1.5, 1.5], "texture": "#0"},
				"east": {"uv": [0.5, 0.5, 1.5, 1.5], "texture": "#0"},
				"south": {"uv": [0.5, 0.5, 1.5, 1.5], "texture": "#0"},
				"west": {"uv": [0.5, 0.5, 1.5, 1.5], "texture": "#0"},
				"up": {"uv": [0.5, 0.5, 1.5, 1.5], "texture": "#0"},
				"down": {"uv": [0.5, 0.5, 1.5, 1.5], "texture": "#0"}
			}
		},
		{
			"from": [7.5, 8, 10],
			"to": [8.5, 9, 13],
			"rotation": {"angle": 22.5, "axis": "x", "origin": [8, 9, 13]},
			"faces": {
				"north": {"uv": [0.5, 0.5, 1.5, 1.5], "texture": "#0"},
				"east": {"uv": [0.5, 0.5, 1.5, 1.5], "texture": "#0"},
				"south": {"uv": [0.5, 0.5, 1.5, 1.5], "texture": "#0"},
				"west": {"uv": [0.5, 0.5, 1.5, 1.5], "texture": "#0"},
				"up": {"uv": [0.5, 0.5, 1.5, 1.5], "texture": "#0"},
				"down": {"uv": [0.5, 0.5, 1.5, 1.5], "texture": "#0"}
			}
		},
		{
			"from": [7.625, 5, 12],
			"to": [8.375, 8, 13],
			"rotation": {"angle": 45, "axis": "x", "origin": [8, 8, 13]},
			"faces": {
				"north": {"uv": [0.5, 2.5, 1.5, 3.5], "texture": "#0"},
				"east": {"uv": [0.5, 2.5, 1.5, 3.5], "texture": "#0"},
				"south": {"uv": [0.5, 2.5, 1.5, 3.5], "texture": "#0"},
				"west": {"uv": [0.5, 2.5, 1.5, 3.5], "texture": "#0"},
				"up": {"uv": [0.5, 2.5, 1.5, 3.5], "texture": "#0"},
				"down": {"uv": [0.5, 2.5, 1.5, 3.5], "texture": "#0"}
			}
		},
		{
			"from": [7.625, 5, 11],
			"to": [8.375, 8, 12],
			"rotation": {"angle": 0, "axis": "x", "origin": [8, 8, 13]},
			"faces": {
				"north": {"uv": [0.5, 2.5, 1.5, 3.5], "texture": "#0"},
				"east": {"uv": [0.5, 2.5, 1.5, 3.5], "texture": "#0"},
				"south": {"uv": [0.5, 2.5, 1.5, 3.5], "texture": "#0"},
				"west": {"uv": [0.5, 2.5, 1.5, 3.5], "texture": "#0"},
				"up": {"uv": [0.5, 2.5, 1.5, 3.5], "texture": "#0"},
				"down": {"uv": [0.5, 2.5, 1.5, 3.5], "texture": "#0"}
			}
		},
		{
			"from": [7.625, 5, 11],
			"to": [8.375, 7, 12],
			"rotation": {"angle": 45, "axis": "x", "origin": [8, 8, 13]},
			"faces": {
				"north": {"uv": [0.5, 2.5, 1.5, 3.5], "texture": "#0"},
				"east": {"uv": [0.5, 2.5, 1.5, 3.5], "texture": "#0"},
				"south": {"uv": [0.5, 2.5, 1.5, 3.5], "texture": "#0"},
				"west": {"uv": [0.5, 2.5, 1.5, 3.5], "texture": "#0"},
				"up": {"uv": [0.5, 2.5, 1.5, 3.5], "texture": "#0"},
				"down": {"uv": [0.5, 2.5, 1.5, 3.5], "texture": "#0"}
			}
		},
		{
			"from": [7.5, 7.5, 9.5],
			"to": [8.5, 8.5, 10.5],
			"rotation": {"angle": -45, "axis": "x", "origin": [8, 8, 10]},
			"faces": {
				"north": {"uv": [0.5, 0.5, 1.5, 1.5], "texture": "#0"},
				"east": {"uv": [0.5, 0.5, 1.5, 1.5], "texture": "#0"},
				"south": {"uv": [0.5, 0.5, 1.5, 1.5], "texture": "#0"},
				"west": {"uv": [0.5, 0.5, 1.5, 1.5], "texture": "#0"},
				"up": {"uv": [0.5, 0.5, 1.5, 1.5], "texture": "#0"},
				"down": {"uv": [0.5, 0.5, 1.5, 1.5], "texture": "#0"}
			}
		},
		{
			"from": [7.5, 6.5, 6],
			"to": [8.5, 8, 7],
			"faces": {
				"north": {"uv": [0.5, 0.5, 1.5, 1.5], "texture": "#0"},
				"east": {"uv": [0.5, 0.5, 1.5, 1.5], "texture": "#0"},
				"south": {"uv": [0.5, 0.5, 1.5, 1.5], "texture": "#0"},
				"west": {"uv": [0.5, 0.5, 1.5, 1.5], "texture": "#0"},
				"up": {"uv": [0.5, 0.5, 1.5, 1.5], "texture": "#0"},
				"down": {"uv": [0.5, 0.5, 1.5, 1.5], "texture": "#0"}
			}
		},
		{
			"from": [7.5, 7, 4.5],
			"to": [8.5, 8.5, 6.5],
			"faces": {
				"north": {"uv": [0.5, 0.5, 1.5, 1.5], "texture": "#0"},
				"east": {"uv": [0.5, 0.5, 1.5, 1.5], "texture": "#0"},
				"south": {"uv": [0.5, 0.5, 1.5, 1.5], "texture": "#0"},
				"west": {"uv": [0.5, 0.5, 1.5, 1.5], "texture": "#0"},
				"up": {"uv": [0.5, 0.5, 1.5, 1.5], "texture": "#0"},
				"down": {"uv": [0.5, 0.5, 1.5, 1.5], "texture": "#0"}
			}
		},
		{
			"from": [7.5, 8, 1],
			"to": [8.5, 8.5, 7],
			"faces": {
				"north": {"uv": [0.5, 0.5, 1.5, 1.5], "texture": "#0"},
				"east": {"uv": [0.5, 0.5, 1.5, 1.5], "texture": "#0"},
				"south": {"uv": [0.5, 0.5, 1.5, 1.5], "texture": "#0"},
				"west": {"uv": [0.5, 0.5, 1.5, 1.5], "texture": "#0"},
				"up": {"uv": [0.5, 0.5, 1.5, 1.5], "texture": "#0"},
				"down": {"uv": [0.5, 0.5, 1.5, 1.5], "texture": "#0"}
			}
		},
		{
			"from": [8.25, 8.5, 1],
			"to": [8.5, 9.5, 1.5],
			"faces": {
				"north": {"uv": [0.5, 0.5, 1.5, 1.5], "texture": "#0"},
				"east": {"uv": [0.5, 0.5, 1.5, 1.5], "texture": "#0"},
				"south": {"uv": [0.5, 0.5, 1.5, 1.5], "texture": "#0"},
				"west": {"uv": [0.5, 0.5, 1.5, 1.5], "texture": "#0"},
				"up": {"uv": [0.5, 0.5, 1.5, 1.5], "texture": "#0"},
				"down": {"uv": [0.5, 0.5, 1.5, 1.5], "texture": "#0"}
			}
		},
		{
			"from": [7.25, 8.5, 3],
			"to": [8.75, 9.5, 4],
			"faces": {
				"north": {"uv": [2.5, 2.5, 5.5, 5.5], "texture": "#0"},
				"east": {"uv": [2.5, 2.5, 5.5, 5.5], "texture": "#0"},
				"south": {"uv": [2.5, 2.5, 5.5, 5.5], "texture": "#0"},
				"west": {"uv": [2.5, 2.5, 5.5, 5.5], "texture": "#0"},
				"up": {"uv": [2.5, 2.5, 5.5, 5.5], "texture": "#0"},
				"down": {"uv": [2.5, 2.5, 5.5, 5.5], "texture": "#0"}
			}
		},
		{
			"from": [7.25, 7.5, 4.75],
			"to": [8.75, 9, 6.25],
			"faces": {
				"north": {"uv": [2.5, 2.5, 5.5, 5.5], "texture": "#0"},
				"east": {"uv": [2.5, 2.5, 5.5, 5.5], "texture": "#0"},
				"south": {"uv": [2.5, 2.5, 5.5, 5.5], "texture": "#0"},
				"west": {"uv": [2.5, 2.5, 5.5, 5.5], "texture": "#0"},
				"up": {"uv": [2.5, 2.5, 5.5, 5.5], "texture": "#0"},
				"down": {"uv": [2.5, 2.5, 5.5, 5.5], "texture": "#0"}
			}
		},
		{
			"from": [7.5, 8, 3],
			"to": [8.5, 9, 4],
			"rotation": {"angle": 45, "axis": "x", "origin": [8, 8, 3]},
			"faces": {
				"north": {"uv": [0.5, 0.5, 1.5, 1.5], "texture": "#0"},
				"east": {"uv": [0.5, 0.5, 1.5, 1.5], "texture": "#0"},
				"south": {"uv": [0.5, 0.5, 1.5, 1.5], "texture": "#0"},
				"west": {"uv": [0.5, 0.5, 1.5, 1.5], "texture": "#0"},
				"up": {"uv": [0.5, 0.5, 1.5, 1.5], "texture": "#0"},
				"down": {"uv": [0.5, 0.5, 1.5, 1.5], "texture": "#0"}
			}
		},
		{
			"from": [7.5, 7.29289, 3.70711],
			"to": [8.5, 8.29289, 6.70711],
			"rotation": {"angle": 22.5, "axis": "x", "origin": [8, 7.29289, 3.70711]},
			"faces": {
				"north": {"uv": [0.5, 0.5, 1.5, 1.5], "texture": "#0"},
				"east": {"uv": [0.5, 0.5, 1.5, 1.5], "texture": "#0"},
				"south": {"uv": [0.5, 0.5, 1.5, 1.5], "texture": "#0"},
				"west": {"uv": [0.5, 0.5, 1.5, 1.5], "texture": "#0"},
				"up": {"uv": [0.5, 0.5, 1.5, 1.5], "texture": "#0"},
				"down": {"uv": [0.5, 0.5, 1.5, 1.5], "texture": "#0"}
			}
		},
		{
			"from": [7.5, 6.14484, 6.47875],
			"to": [8.5, 6.64484, 7.47875],
			"rotation": {"angle": 0, "axis": "x", "origin": [8, 6.14484, 6.47875]},
			"faces": {
				"north": {"uv": [0.5, 0.5, 1.5, 1.5], "texture": "#0"},
				"east": {"uv": [0.5, 0.5, 1.5, 1.5], "texture": "#0"},
				"south": {"uv": [0.5, 0.5, 1.5, 1.5], "texture": "#0"},
				"west": {"uv": [0.5, 0.5, 1.5, 1.5], "texture": "#0"},
				"up": {"uv": [0.5, 0.5, 1.5, 1.5], "texture": "#0"},
				"down": {"uv": [0.5, 0.5, 1.5, 1.5], "texture": "#0"}
			}
		},
		{
			"from": [7.5, 6.14484, 7.47875],
			"to": [8.5, 6.64484, 8.47875],
			"rotation": {"angle": -22.5, "axis": "x", "origin": [8, 6.14484, 7.47875]},
			"faces": {
				"north": {"uv": [0.5, 0.5, 1.5, 1.5], "texture": "#0"},
				"east": {"uv": [0.5, 0.5, 1.5, 1.5], "texture": "#0"},
				"south": {"uv": [0.5, 0.5, 1.5, 1.5], "texture": "#0"},
				"west": {"uv": [0.5, 0.5, 1.5, 1.5], "texture": "#0"},
				"up": {"uv": [0.5, 0.5, 1.5, 1.5], "texture": "#0"},
				"down": {"uv": [0.5, 0.5, 1.5, 1.5], "texture": "#0"}
			}
		},
		{
			"from": [7.75, 8.5, 1],
			"to": [8.25, 9.5, 3],
			"faces": {
				"north": {"uv": [2.5, 0.5, 3.5, 1.5], "texture": "#0"},
				"east": {"uv": [2.5, 0.5, 3.5, 1.5], "texture": "#0"},
				"south": {"uv": [2.5, 0.5, 3.5, 1.5], "texture": "#0"},
				"west": {"uv": [2.5, 0.5, 3.5, 1.5], "texture": "#0"},
				"up": {"uv": [2.5, 0.5, 3.5, 1.5], "texture": "#0"},
				"down": {"uv": [2.5, 0.5, 3.5, 1.5], "texture": "#0"}
			}
		},
		{
			"from": [7.75, 9, -1],
			"to": [8.25, 9.5, 1],
			"faces": {
				"north": {"uv": [2.5, 0.5, 3.5, 1.5], "texture": "#0"},
				"east": {"uv": [2.5, 0.5, 3.5, 1.5], "texture": "#0"},
				"south": {"uv": [2.5, 0.5, 3.5, 1.5], "texture": "#0"},
				"west": {"uv": [2.5, 0.5, 3.5, 1.5], "texture": "#0"},
				"up": {"uv": [2.5, 0.5, 3.5, 1.5], "texture": "#0"},
				"down": {"uv": [2.5, 0.5, 3.5, 1.5], "texture": "#0"}
			}
		},
		{
			"from": [7.75, 9, -1],
			"to": [8.25, 9.7071, -0.2929],
			"rotation": {"angle": -45, "axis": "x", "origin": [8, 9, -1]},
			"faces": {
				"north": {"uv": [2.5, 0.5, 3.5, 1.5], "texture": "#0"},
				"east": {"uv": [2.5, 0.5, 3.5, 1.5], "texture": "#0"},
				"south": {"uv": [2.5, 0.5, 3.5, 1.5], "texture": "#0"},
				"west": {"uv": [2.5, 0.5, 3.5, 1.5], "texture": "#0"},
				"up": {"uv": [2.5, 0.5, 3.5, 1.5], "texture": "#0"},
				"down": {"uv": [2.5, 0.5, 3.5, 1.5], "texture": "#0"}
			}
		},
		{
			"from": [7.5, 8.5, 2.5],
			"to": [8.5, 9.5, 7],
			"faces": {
				"north": {"uv": [0.5, 0.5, 1.5, 1.5], "texture": "#0"},
				"east": {"uv": [0.5, 0.5, 1.5, 1.5], "texture": "#0"},
				"south": {"uv": [0.5, 0.5, 1.5, 1.5], "texture": "#0"},
				"west": {"uv": [0.5, 0.5, 1.5, 1.5], "texture": "#0"},
				"up": {"uv": [0.5, 0.5, 1.5, 1.5], "texture": "#0"},
				"down": {"uv": [0.5, 0.5, 1.5, 1.5], "texture": "#0"}
			}
		},
		{
			"from": [7.5, 9, 7],
			"to": [8.5, 10, 11],
			"faces": {
				"north": {"uv": [0.5, 0.5, 1.5, 1.5], "texture": "#0"},
				"east": {"uv": [0.5, 0.5, 1.5, 1.5], "texture": "#0"},
				"south": {"uv": [0.5, 0.5, 1.5, 1.5], "texture": "#0"},
				"west": {"uv": [0.5, 0.5, 1.5, 1.5], "texture": "#0"},
				"up": {"uv": [0.5, 0.5, 1.5, 1.5], "texture": "#0"},
				"down": {"uv": [0.5, 0.5, 1.5, 1.5], "texture": "#0"}
			}
		},
		{
			"from": [7.5, 10, 8],
			"to": [8.5, 11.5, 11],
			"faces": {
				"north": {"uv": [0.5, 0.5, 1.5, 1.5], "texture": "#0"},
				"east": {"uv": [0.5, 0.5, 1.5, 1.5], "texture": "#0"},
				"south": {"uv": [0.5, 0.5, 1.5, 1.5], "texture": "#0"},
				"west": {"uv": [0.5, 0.5, 1.5, 1.5], "texture": "#0"},
				"up": {"uv": [0.5, 0.5, 1.5, 1.5], "texture": "#0"},
				"down": {"uv": [0.5, 0.5, 1.5, 1.5], "texture": "#0"}
			}
		},
		{
			"from": [7.625, 9, 11],
			"to": [8.375, 11, 12],
			"faces": {
				"north": {"uv": [2.5, 0.5, 3.5, 1.5], "texture": "#0"},
				"east": {"uv": [2.5, 0.5, 3.5, 1.5], "texture": "#0"},
				"south": {"uv": [2.5, 0.5, 3.5, 1.5], "texture": "#0"},
				"west": {"uv": [2.5, 0.5, 3.5, 1.5], "texture": "#0"},
				"up": {"uv": [2.5, 0.5, 3.5, 1.5], "texture": "#0"},
				"down": {"uv": [2.5, 0.5, 3.5, 1.5], "texture": "#0"}
			}
		},
		{
			"from": [7.625, 11.5, 8],
			"to": [8.375, 12, 11],
			"faces": {
				"north": {"uv": [2.5, 0.5, 3.5, 1.5], "texture": "#0"},
				"east": {"uv": [2.5, 0.5, 3.5, 1.5], "texture": "#0"},
				"south": {"uv": [2.5, 0.5, 3.5, 1.5], "texture": "#0"},
				"west": {"uv": [2.5, 0.5, 3.5, 1.5], "texture": "#0"},
				"up": {"uv": [2.5, 0.5, 3.5, 1.5], "texture": "#0"},
				"down": {"uv": [2.5, 0.5, 3.5, 1.5], "texture": "#0"}
			}
		},
		{
			"from": [7.5, 11.5, 3.5],
			"to": [8.5, 11.75, 8],
			"faces": {
				"north": {"uv": [0.5, 4.5, 1.5, 5.5], "texture": "#0"},
				"east": {"uv": [0.5, 8.5, 8.5, 9.5], "texture": "#0"},
				"south": {"uv": [0.5, 4.5, 1.5, 5.5], "texture": "#0"},
				"west": {"uv": [0.5, 8.5, 8.5, 9.5], "texture": "#0"},
				"up": {"uv": [0.5, 8.5, 8.5, 9.5], "rotation": 90, "texture": "#0"},
				"down": {"uv": [0.5, 8.5, 8.5, 9.5], "rotation": 90, "texture": "#0"}
			}
		},
		{
			"from": [7.625, 11.5, 11],
			"to": [8.375, 12.5, 12],
			"faces": {
				"north": {"uv": [0.5, 0.5, 1.5, 1.5], "texture": "#0"},
				"east": {"uv": [8.5, 0.5, 11.5, 3.5], "texture": "#0"},
				"south": {"uv": [0.5, 0.5, 1.5, 1.5], "texture": "#0"},
				"west": {"uv": [8.5, 0.5, 11.5, 3.5], "texture": "#0"},
				"up": {"uv": [0.5, 0.5, 1.5, 1.5], "texture": "#0"},
				"down": {"uv": [0.5, 0.5, 1.5, 1.5], "texture": "#0"}
			}
		},
		{
			"from": [6.75, 10.25, 3.5],
			"to": [7.25, 11.25, 9],
			"faces": {
				"north": {"uv": [0.5, 4.5, 1.5, 5.5], "texture": "#0"},
				"east": {"uv": [0.5, 4.5, 1.5, 5.5], "texture": "#0"},
				"south": {"uv": [0.5, 4.5, 1.5, 5.5], "texture": "#0"},
				"west": {"uv": [0.5, 8.5, 8.5, 9.5], "texture": "#0"},
				"up": {"uv": [0.5, 8.5, 8.5, 9.5], "rotation": 90, "texture": "#0"},
				"down": {"uv": [0.5, 8.5, 8.5, 9.5], "rotation": 90, "texture": "#0"}
			}
		},
		{
			"from": [8.5, 10.25, 3.5],
			"to": [9, 11.25, 9],
			"faces": {
				"north": {"uv": [2.5, 6.5, 3.5, 7.5], "texture": "#0"},
				"east": {"uv": [2.5, 6.5, 3.5, 7.5], "texture": "#0"},
				"south": {"uv": [2.5, 6.5, 3.5, 7.5], "texture": "#0"},
				"west": {"uv": [2.5, 6.5, 3.5, 7.5], "texture": "#0"},
				"up": {"uv": [2.5, 6.5, 3.5, 7.5], "texture": "#0"},
				"down": {"uv": [2.5, 6.5, 3.5, 7.5], "texture": "#0"}
			}
		},
		{
			"from": [8.5, 9.25, 5],
			"to": [9, 10.25, 7.5],
			"faces": {
				"north": {"uv": [2.5, 6.5, 3.5, 7.5], "texture": "#0"},
				"east": {"uv": [2.5, 6.5, 3.5, 7.5], "texture": "#0"},
				"south": {"uv": [2.5, 6.5, 3.5, 7.5], "texture": "#0"},
				"west": {"uv": [2.5, 6.5, 3.5, 7.5], "texture": "#0"},
				"up": {"uv": [2.5, 6.5, 3.5, 7.5], "texture": "#0"},
				"down": {"uv": [2.5, 6.5, 3.5, 7.5], "texture": "#0"}
			}
		},
		{
			"from": [8.5, 9.75, -1],
			"to": [8.75, 10.25, 10],
			"faces": {
				"north": {"uv": [0.5, 4.5, 1.5, 5.5], "texture": "#0"},
				"east": {"uv": [0.5, 8.5, 8.5, 9.5], "texture": "#0"},
				"south": {"uv": [0.5, 4.5, 1.5, 5.5], "texture": "#0"},
				"west": {"uv": [0.5, 8.5, 8.5, 9.5], "texture": "#0"},
				"up": {"uv": [0.5, 8.5, 8.5, 9.5], "rotation": 90, "texture": "#0"},
				"down": {"uv": [0.5, 8.5, 8.5, 9.5], "rotation": 90, "texture": "#0"}
			}
		},
		{
			"from": [6.75, 10.25, 8.5],
			"to": [8.25, 11.25, 9],
			"rotation": {"angle": -45, "axis": "y", "origin": [6.75, 8, 9]},
			"faces": {
				"north": {"uv": [0.5, 4.5, 1.5, 5.5], "texture": "#0"},
				"east": {"uv": [0.5, 4.5, 1.5, 5.5], "texture": "#0"},
				"south": {"uv": [0.5, 4.5, 1.5, 5.5], "texture": "#0"},
				"west": {"uv": [0.5, 4.5, 1.5, 5.5], "texture": "#0"},
				"up": {"uv": [0.5, 4.5, 1.5, 5.5], "texture": "#0"},
				"down": {"uv": [0.5, 4.5, 1.5, 5.5], "texture": "#0"}
			}
		},
		{
			"from": [7.5, 10.25, -2],
			"to": [8.5, 11.25, 8],
			"faces": {
				"north": {"uv": [2.5, 0.5, 3.5, 1.5], "texture": "#0"},
				"east": {"uv": [2.5, 0.5, 3.5, 1.5], "texture": "#0"},
				"south": {"uv": [2.5, 0.5, 3.5, 1.5], "texture": "#0"},
				"west": {"uv": [2.5, 0.5, 3.5, 1.5], "texture": "#0"},
				"up": {"uv": [2.5, 0.5, 3.5, 1.5], "texture": "#0"},
				"down": {"uv": [2.5, 0.5, 3.5, 1.5], "texture": "#0"}
			}
		},
		{
			"from": [7.5, 10.25, -4.5],
			"to": [8.5, 11.25, -3],
			"rotation": {"angle": 22.5, "axis": "y", "origin": [7.5, 10.75, -3]},
			"faces": {
				"north": {"uv": [4.5, 0.5, 5.5, 1.5], "texture": "#0"},
				"east": {"uv": [4.5, 0.5, 5.5, 1.5], "texture": "#0"},
				"south": {"uv": [4.5, 0.5, 5.5, 1.5], "texture": "#0"},
				"west": {"uv": [4.5, 0.5, 5.5, 1.5], "texture": "#0"},
				"up": {"uv": [6.5, 0.5, 7.5, 1.5], "texture": "#0"},
				"down": {"uv": [6.5, 0.5, 7.5, 1.5], "texture": "#0"}
			}
		},
		{
			"from": [7.5, 10.25, -4.5],
			"to": [8.5, 11.25, -3],
			"rotation": {"angle": -22.5, "axis": "y", "origin": [8.5, 10.75, -3]},
			"faces": {
				"north": {"uv": [4.5, 0.5, 5.5, 1.5], "texture": "#0"},
				"east": {"uv": [4.5, 0.5, 5.5, 1.5], "texture": "#0"},
				"south": {"uv": [4.5, 0.5, 5.5, 1.5], "texture": "#0"},
				"west": {"uv": [4.5, 0.5, 5.5, 1.5], "texture": "#0"},
				"up": {"uv": [6.5, 0.5, 7.5, 1.5], "texture": "#0"},
				"down": {"uv": [6.5, 0.5, 7.5, 1.5], "texture": "#0"}
			}
		},
		{
			"from": [7.5, 10.25, -4.5],
			"to": [8.5, 11.25, -3],
			"rotation": {"angle": 22.5, "axis": "x", "origin": [7.5, 11.25, -3]},
			"faces": {
				"north": {"uv": [4.5, 0.5, 5.5, 1.5], "texture": "#0"},
				"east": {"uv": [6.5, 0.5, 7.5, 1.5], "texture": "#0"},
				"south": {"uv": [4.5, 0.5, 5.5, 1.5], "texture": "#0"},
				"west": {"uv": [6.5, 0.5, 7.5, 1.5], "texture": "#0"},
				"up": {"uv": [4.5, 0.5, 5.5, 1.5], "texture": "#0"},
				"down": {"uv": [4.5, 0.5, 5.5, 1.5], "texture": "#0"}
			}
		},
		{
			"from": [7.5, 10.25, -4.5],
			"to": [8.5, 11.25, -3],
			"rotation": {"angle": -22.5, "axis": "x", "origin": [7.5, 10.25, -3]},
			"faces": {
				"north": {"uv": [4.5, 0.5, 5.5, 1.5], "texture": "#0"},
				"east": {"uv": [6.5, 0.5, 7.5, 1.5], "texture": "#0"},
				"south": {"uv": [4.5, 0.5, 5.5, 1.5], "texture": "#0"},
				"west": {"uv": [6.5, 0.5, 7.5, 1.5], "texture": "#0"},
				"up": {"uv": [4.5, 0.5, 5.5, 1.5], "texture": "#0"},
				"down": {"uv": [4.5, 0.5, 5.5, 1.5], "texture": "#0"}
			}
		},
		{
			"from": [7.25, 10, -3],
			"to": [8.75, 11.5, -2],
			"faces": {
				"north": {"uv": [4.5, 0.5, 5.5, 1.5], "texture": "#0"},
				"east": {"uv": [4.5, 0.5, 5.5, 1.5], "texture": "#0"},
				"south": {"uv": [4.5, 0.5, 5.5, 1.5], "texture": "#0"},
				"west": {"uv": [4.5, 0.5, 5.5, 1.5], "texture": "#0"},
				"up": {"uv": [4.5, 0.5, 5.5, 1.5], "texture": "#0"},
				"down": {"uv": [4.5, 0.5, 5.5, 1.5], "texture": "#0"}
			}
		},
		{
			"from": [6.92595, 9.67597, -5.38583],
			"to": [9.07405, 11.82403, -4.38582],
			"rotation": {"angle": 0, "axis": "z", "origin": [7.39866, 10.77249, -4.881]},
			"faces": {
				"north": {"uv": [0.5, 0.5, 1.5, 1.5], "texture": "#0"},
				"east": {"uv": [0.5, 0.5, 1.5, 1.5], "texture": "#0"},
				"south": {"uv": [0.5, 0.5, 1.5, 1.5], "texture": "#0"},
				"west": {"uv": [0.5, 0.5, 1.5, 1.5], "texture": "#0"},
				"up": {"uv": [0.5, 0.5, 1.5, 1.5], "texture": "#0"},
				"down": {"uv": [0.5, 0.5, 1.5, 1.5], "texture": "#0"}
			}
		},
		{
			"from": [7.5, 9.5, 1],
			"to": [8.5, 10, 7],
			"faces": {
				"north": {"uv": [0.5, 0.5, 1.5, 1.5], "texture": "#0"},
				"east": {"uv": [0.5, 0.5, 1.5, 1.5], "texture": "#0"},
				"south": {"uv": [0.5, 0.5, 1.5, 1.5], "texture": "#0"},
				"west": {"uv": [0.5, 0.5, 1.5, 1.5], "texture": "#0"},
				"up": {"uv": [0.5, 0.5, 1.5, 1.5], "texture": "#0"},
				"down": {"uv": [0.5, 0.5, 1.5, 1.5], "texture": "#0"}
			}
		},
		{
			"from": [7.5, 9.5, -1.5],
			"to": [8.5, 10, 1],
			"faces": {
				"north": {"uv": [0.5, 0.5, 1.5, 1.5], "texture": "#0"},
				"east": {"uv": [0.5, 0.5, 1.5, 1.5], "texture": "#0"},
				"south": {"uv": [0.5, 0.5, 1.5, 1.5], "texture": "#0"},
				"west": {"uv": [0.5, 0.5, 1.5, 1.5], "texture": "#0"},
				"up": {"uv": [0.5, 0.5, 1.5, 1.5], "texture": "#0"},
				"down": {"uv": [0.5, 0.5, 1.5, 1.5], "texture": "#0"}
			}
		}
	],
	"display": {
		"thirdperson_righthand": {
			"translation": [0, 0.5, -1.5],
			"scale": [0.5, 0.5, 0.5]
		},
		"thirdperson_lefthand": {
			"translation": [0, 0.5, -1.5],
			"scale": [0.5, 0.5, 0.5]
		},
		"firstperson_righthand": {
			"rotation": [0, 5, 0],
			"translation": [-0.5, 4, 0],
			"scale": [0.85, 0.85, 0.85]
		},
		"firstperson_lefthand": {
			"rotation": [0, 5, 0],
			"translation": [-0.5, 4, 0],
			"scale": [0.85, 0.85, 0.85]
		},
		"ground": {
			"translation": [0, 7.25, 0]
		},
		"gui": {
			"rotation": [0, -90, 0],
			"translation": [-3.5, 0, 0],
			"scale": [0.85, 0.85, 0.85]
		},
		"head": {
			"translation": [0, 12.75, 0]
		},
		"fixed": {
			"rotation": [0, 90, 0],
			"translation": [4, 0, 0]
		}
	}
}