{
	"file_name": "right_arm",
	"texture_size": [
		128,
		128
	],
	"textures": {
		"layer0": "modelengine:entity/metro_cop"
	},
	"elements": [
		{
			"name": "right_arm_0",
			"from": [
				7.9999995,
				4.46,
				6.8599997
			],
			"to": [
				9.68,
				9.139999,
				9.139999
			],
			"rotation": {
				"angle": 0.0,
				"axis": "z",
				"origin": [
					8.0,
					8.0,
					8.0
				]
			},
			"faces": {
				"down": {
					"uv": [
						3.75,
						11.625,
						4.125,
						12.125
					],
					"texture": "#layer0",
					"tintindex": 0
				},
				"east": {
					"uv": [
						2.875,
						12.125,
						3.375,
						13.125
					],
					"texture": "#layer0",
					"tintindex": 0
				},
				"north": {
					"uv": [
						3.375,
						12.125,
						3.75,
						13.125
					],
					"texture": "#layer0",
					"tintindex": 0
				},
				"south": {
					"uv": [
						4.25,
						12.125,
						4.625,
						13.125
					],
					"texture": "#layer0",
					"tintindex": 0
				},
				"up": {
					"uv": [
						3.75,
						12.125,
						3.375,
						11.625
					],
					"texture": "#layer0",
					"tintindex": 0
				},
				"west": {
					"uv": [
						3.75,
						12.125,
						4.25,
						13.125
					],
					"texture": "#layer0",
					"tintindex": 0
				}
			}
		}
	],
	"display": {
		"head": {
			"translation": [
				0.0,
				-6.4,
				0.0
			],
			"rotation": [
				0.0,
				0.0,
				0.0
			],
			"scale": [
				3.8095,
				3.8095,
				3.8095
			]
		},
		"gui": {
			"translation": [
				0.0,
				0.0,
				0.0
			],
			"rotation": [
				35.0,
				225.0,
				0.0
			],
			"scale": [
				0.625,
				0.625,
				0.625
			]
		}
	}
}