{
	"file_name": "main_body",
	"texture_size": [
		128,
		128
	],
	"textures": {
		"layer0": "modelengine:entity/dwerthraul"
	},
	"elements": [
		{
			"name": "main_body_0",
			"from": [
				6.5,
				8.0,
				4.3999996
			],
			"to": [
				9.5,
				15.2,
				11.6
			],
			"rotation": {
				"angle": 0.0,
				"axis": "z",
				"origin": [
					8.0,
					8.0,
					8.0
				]
			},
			"faces": {
				"down": {
					"uv": [
						6.25,
						0.0,
						6.875,
						1.5
					],
					"texture": "#layer0",
					"tintindex": 0
				},
				"east": {
					"uv": [
						4.125,
						1.5,
						5.625,
						3.0
					],
					"texture": "#layer0",
					"tintindex": 0
				},
				"north": {
					"uv": [
						5.625,
						1.5,
						6.25,
						3.0
					],
					"texture": "#layer0",
					"tintindex": 0
				},
				"south": {
					"uv": [
						7.75,
						1.5,
						8.375,
						3.0
					],
					"texture": "#layer0",
					"tintindex": 0
				},
				"up": {
					"uv": [
						6.25,
						1.5,
						5.625,
						0.0
					],
					"texture": "#layer0",
					"tintindex": 0
				},
				"west": {
					"uv": [
						6.25,
						1.5,
						7.75,
						3.0
					],
					"texture": "#layer0",
					"tintindex": 0
				}
			}
		},
		{
			"name": "main_body_1",
			"from": [
				8.0,
				15.2,
				6.2
			],
			"to": [
				8.0,
				20.600002,
				15.8
			],
			"rotation": {
				"angle": 0.0,
				"axis": "z",
				"origin": [
					8.0,
					8.0,
					8.0
				]
			},
			"faces": {
				"down": {
					"uv": [
						4.125,
						4.125,
						4.125,
						6.125
					],
					"texture": "#layer0",
					"tintindex": 0
				},
				"east": {
					"uv": [
						2.125,
						6.125,
						4.125,
						7.25
					],
					"texture": "#layer0",
					"tintindex": 0
				},
				"north": {
					"uv": [
						4.125,
						6.125,
						4.125,
						7.25
					],
					"texture": "#layer0",
					"tintindex": 0
				},
				"south": {
					"uv": [
						6.125,
						6.125,
						6.125,
						7.25
					],
					"texture": "#layer0",
					"tintindex": 0
				},
				"up": {
					"uv": [
						4.125,
						6.125,
						4.125,
						4.125
					],
					"texture": "#layer0",
					"tintindex": 0
				},
				"west": {
					"uv": [
						4.125,
						6.125,
						6.125,
						7.25
					],
					"texture": "#layer0",
					"tintindex": 0
				}
			}
		}
	],
	"display": {
		"head": {
			"translation": [
				0.0,
				-6.4,
				0.0
			],
			"rotation": [
				0.0,
				0.0,
				0.0
			],
			"scale": [
				3.8095,
				3.8095,
				3.8095
			]
		},
		"gui": {
			"translation": [
				0.0,
				0.0,
				0.0
			],
			"rotation": [
				35.0,
				225.0,
				0.0
			],
			"scale": [
				0.625,
				0.625,
				0.625
			]
		}
	}
}